{
  "$schema": "https://developer.microsoft.com/json-schemas/spfx-build/package-solution.schema.json",
  "solution": {
    "name": "communities-client-side-solution",
    "id": "2539de61-5801-4cfe-b54a-c0888fa4085e",
    "version": "1.0.0.0",
    "includeClientSideAssets": true,
    "skipFeatureDeployment": true,
    "webApiPermissionRequests": [
      {
        "resource": "Microsoft Graph",
        "scope": "Group.Read.All"
      }
    ],
    "isDomainIsolated": false,
    "developer": {
      "name": "",
      "websiteUrl": "",
      "privacyUrl": "",
      "termsOfUseUrl": "",
      "mpnId": "Undefined-1.18.2"
    },
    "metadata": {
      "shortDescription": {
        "default": "Communities description"
      },
      "longDescription": {
        "default": "Communities description"
      },
      "screenshotPaths": [],
      "videoUrl": "",
      "categories": []
    },
    "features": [
      {
        "title": "communities Feature",
        "description": "The feature that activates elements of the communities solution.",
        "id": "788e18e0-39aa-438e-ba31-bf792b1ae588",
        "version": "1.0.0.0"
      }
    ]
  },
  "paths": {
    "zippedPackage": "solution/communities.sppkg"
  }
}
